pycloudmesh/__init__.py
pycloudmesh/definitions.py
pycloudmesh/pycloudmesh.py
pycloudmesh/utils.py
pycloudmesh/providers/__init__.py
pycloudmesh/providers/aws.py
pycloudmesh/providers/azure.py
pycloudmesh/providers/gcp.py
pycloudmesh-1.0.4.dist-info/licenses/LICENSE
pycloudmesh-1.0.4.dist-info/METADATA
pycloudmesh-1.0.4.dist-info/WHEEL
pycloudmesh-1.0.4.dist-info/top_level.txt
pycloudmesh-1.0.4.dist-info/RECORD
