Metadata-Version: 2.4
Name: pycloudmesh
Version: 1.0.4
Summary: Unified FinOps and cost analytics toolkit for AWS, Azure, and GCP. Provides programmatic access to cloud cost, budgeting, optimization, and governance APIs.
Home-page: https://github.com/NitheshKG/pycloudmesh
Author: Nithesh
Author-email: nitheshkg18@gmail.com
Classifier: Programming Language :: Python :: 3
Classifier: License :: OSI Approved :: MIT License
Classifier: Operating System :: OS Independent
Requires-Python: >=3.9
License-File: LICENSE
Requires-Dist: boto3>=1.26.0
Requires-Dist: requests>=2.28.0
Requires-Dist: botocore>=1.29.0
Requires-Dist: azure-identity>=1.12.0
Requires-Dist: azure-mgmt-costmanagement>=4.0.0
Requires-Dist: azure-mgmt-consumption>=9.0.0
Requires-Dist: azure-mgmt-billing>=6.0.0
Requires-Dist: azure-mgmt-advisor>=9.0.0
Requires-Dist: azure-mgmt-resource>=23.0.0
Requires-Dist: google-cloud-billing>=1.10.0
Requires-Dist: google-cloud-recommender>=2.8.0
Requires-Dist: google-cloud-billing-budgets>=1.8.0
Requires-Dist: google-cloud-resource-manager>=1.8.0
Requires-Dist: google-cloud-bigquery>=3.9.0
Requires-Dist: google-cloud-asset>=1.8.0
Requires-Dist: google-cloud-org-policy>=1.8.0
Requires-Dist: google-auth>=2.17.0
Requires-Dist: python-dateutil>=2.8.0
Requires-Dist: typing-extensions>=4.0.0
Requires-Dist: python-dotenv>=1.0.0
Requires-Dist: pandas>=1.0.0
Dynamic: author
Dynamic: author-email
Dynamic: classifier
Dynamic: description
Dynamic: description-content-type
Dynamic: home-page
Dynamic: license-file
Dynamic: requires-dist
Dynamic: requires-python
Dynamic: summary
